pytorch_clip_bbox/__init__.py
pytorch_clip_bbox/clip_bbox.py
pytorch_clip_bbox-2021.12.25.0.dist-info/LICENSE
pytorch_clip_bbox-2021.12.25.0.dist-info/METADATA
pytorch_clip_bbox-2021.12.25.0.dist-info/WHEEL
pytorch_clip_bbox-2021.12.25.0.dist-info/top_level.txt
pytorch_clip_bbox-2021.12.25.0.dist-info/zip-safe
pytorch_clip_bbox-2021.12.25.0.dist-info/RECORD
