Metadata-Version: 2.1
Name: pytorch-clip-bbox
Version: 2021.12.25.0
Summary: Pytorch implementation of the CLIP guided bbox refinement for Object Detection.
Home-page: UNKNOWN
Author: Sergei Belousov aka BeS
Author-email: sergei.o.belousov@gmail.com
License: UNKNOWN
Platform: UNKNOWN
Classifier: Programming Language :: Python :: 3
Requires-Dist: Cython
Requires-Dist: cython
Requires-Dist: numpy
Requires-Dist: opencv-python
Requires-Dist: pytorch-clip-guided-loss
Requires-Dist: torch
Requires-Dist: wheel
